mento/__init__.py
mento/metadata.py
mento/trigger.py
mento/utils.py
desy_mento-0.2.1.dist-info/METADATA
desy_mento-0.2.1.dist-info/WHEEL
desy_mento-0.2.1.dist-info/top_level.txt
desy_mento-0.2.1.dist-info/RECORD
