Metadata-Version: 2.1
Name: desy-mento
Version: 0.2.1
Summary: A Python (3.7+ only) package for PETRA-III beamlines at DESY for automatically triggering online data processing jobs like remote data analysis, and local visualization tasks.
Author-email: Vijay Kartik <vijay.kartik@desy.de>
Maintainer-email: DESY FS-SC <fsscuser@mail.desy.de>
License: GNU GENERAL PUBLIC LICENSE
Project-URL: homepage, https://gitlab.desy.de/fs-sc/mento
Project-URL: documentation, https://gitlab.desy.de/fs-sc/mento
Project-URL: repository, https://gitlab.desy.de/fs-sc/mento
Classifier: Development Status :: 4 - Beta
Classifier: Intended Audience :: Science/Research
Classifier: Intended Audience :: Developers
Classifier: License :: OSI Approved :: GNU General Public License v3 or later (GPLv3+)
Classifier: Operating System :: OS Independent
Classifier: Programming Language :: Python :: 3
Classifier: Topic :: Scientific/Engineering
Classifier: Topic :: Software Development :: Libraries :: Python Modules
Requires-Python: >=3.7
Provides-Extra: lint
Requires-Dist: black ; extra == 'lint'
Requires-Dist: flake8 ; extra == 'lint'
Provides-Extra: test
Requires-Dist: pytest ; extra == 'test'
Requires-Dist: pytest-cov ; extra == 'test'
Requires-Dist: coverage ; extra == 'test'
